pgsql_mcp_server/__init__.py
pgsql_mcp_server/app.py
pgsql_mcp_server-1.4.3.dist-info/WHEEL
pgsql_mcp_server-1.4.3.dist-info/entry_points.txt
pgsql_mcp_server-1.4.3.dist-info/METADATA
pgsql_mcp_server-1.4.3.dist-info/RECORD
