Metadata-Version: 2.3
Name: pgsql-mcp-server
Version: 1.4.3
Summary: PostgreSQL MCP Server
Keywords: ai,mcp,postgresql,pgsql,mcp-server,pgsql-mcp-server
Author: curry tang
Author-email: curry tang <twn39@163.com>
License: MIT
Classifier: Intended Audience :: Developers
Classifier: License :: OSI Approved :: MIT License
Classifier: Programming Language :: Python :: 3
Classifier: Programming Language :: Python :: 3.10
Classifier: Programming Language :: Python :: 3.11
Classifier: Programming Language :: Python :: 3.12
Requires-Dist: asyncpg>=0.31.0
Requires-Dist: click>=8.3.1
Requires-Dist: httpx>=0.28.1
Requires-Dist: mcp[cli]>=1.24.0
Requires-Dist: python-dotenv>=1.2.1
Requires-Dist: sqlmodel>=0.0.27
Requires-Dist: sqlalchemy[asyncio]>=2.0.45
Requires-Dist: tabulate>=0.9.0
Requires-Dist: h11>=0.16.0
Requires-Dist: pip>=25.3
Requires-Dist: starlette>=0.50.0
Maintainer: curry tang
Maintainer-email: curry tang <twn39@163.com>
Requires-Python: >=3.10
Project-URL: Documentation, https://github.com/twn39/pgsql-mcp-server
Project-URL: Homepage, https://github.com/twn39/pgsql-mcp-server
Project-URL: Repository, https://github.com/twn39/pgsql-mcp-server
Project-URL: Source Code, https://github.com/twn39/pgsql-mcp-server
